LICENSE
README.md
pyproject.toml
setup.cfg
setup.py
Boyoke_Encok.egg-info/PKG-INFO
Boyoke_Encok.egg-info/SOURCES.txt
Boyoke_Encok.egg-info/dependency_links.txt
Boyoke_Encok.egg-info/requires.txt
Boyoke_Encok.egg-info/top_level.txt
boyoke_encok/__init__.py
boyoke_encok/base.py
boyoke_encok.egg-info/PKG-INFO
boyoke_encok.egg-info/SOURCES.txt
boyoke_encok.egg-info/dependency_links.txt
boyoke_encok.egg-info/requires.txt
boyoke_encok.egg-info/top_level.txt